very_based_interface/__about__.py
very_based_interface/__init__.py
very_based_interface/cli.py
very_based_interface/memory_manager.py
very_based_interface/types.py
very_based_interface/vbi_file.py
very_based_interface-0.1.1.dist-info/METADATA
very_based_interface-0.1.1.dist-info/WHEEL
very_based_interface-0.1.1.dist-info/entry_points.txt
very_based_interface-0.1.1.dist-info/licenses/LICENSE.txt
very_based_interface-0.1.1.dist-info/RECORD
