Metadata-Version: 2.3
Name: very-based-interface
Version: 0.1.1
Project-URL: Documentation, https://github.com/xboxoneresearch/very_based_interface#readme
Project-URL: Issues, https://github.com/xboxoneresearch/very_based_interface/issues
Project-URL: Source, https://github.com/xboxoneresearch/very_based_interface
Author: LukeFZ, xboxoneresearch
License-Expression: MIT
License-File: LICENSE.txt
Classifier: Development Status :: 4 - Beta
Classifier: Programming Language :: Python
Classifier: Programming Language :: Python :: 3.11
Classifier: Programming Language :: Python :: 3.12
Classifier: Programming Language :: Python :: Implementation :: CPython
Classifier: Programming Language :: Python :: Implementation :: PyPy
Requires-Python: >=3.8
Requires-Dist: dissect-cstruct~=4.0.0
Requires-Dist: pefile
Requires-Dist: typer
